{
  "project_info": {
    "project_number": "98501371747",
    "project_id": "idle-zombie-invasion",
    "storage_bucket": "idle-zombie-invasion.appspot.com"
  },
  "client": [
    {
      "client_info": {
        "mobilesdk_app_id": "1:98501371747:ios:d79087a11861949d2b9556",
        "android_client_info": {
          "package_name": "com.voyager.idlezombieinvasion"
        }
      },
      "api_key": [
        {
          "current_key": "AIzaSyA0dsiUrzm5wgwiiEK-GTLUBS262yTyBc8"
        }
      ],
      "services": {
        "analytics_service": {
          "status": 0
        },
        "appinvite_service": {
          "status": 1
        }
      },
      "oauth_client": [
        {
          "client_id": "98501371747-nnscboocffg80b7s4q2rb39qt2arbv5o.apps.googleusercontent.com"
        }
      ]
    }
  ],
  "configuration_version": "1"
}